README.rst
setup.py
django_slugfield.egg-info/PKG-INFO
django_slugfield.egg-info/SOURCES.txt
django_slugfield.egg-info/dependency_links.txt
django_slugfield.egg-info/top_level.txt
slugfield/__init__.py
slugfield/main.py
test_app/__init__.py
test_app/forms.py
test_app/models.py
test_app/tests.py