Metadata-Version: 1.1
Name: django-slugfield
Version: 0.9
Summary: Django manual slug field
Home-page: https://github.com/dimka665/django-slugfield
Author: Dmitry Voronin
Author-email: dimka665@gmail.com
License: MIT License
Keywords: django slugfield slug field slugify url
Platform: UNKNOWN
Classifier: License :: OSI Approved :: MIT License
Classifier: Programming Language :: Python :: 2
Classifier: Programming Language :: Python :: 2.7
Classifier: Programming Language :: Python :: 3
Classifier: Programming Language :: Python :: 3.3
Classifier: Programming Language :: Python :: 3.4
